README.txt
setup.py
gpsimy/__init__.py
gpsimy.egg-info/PKG-INFO
gpsimy.egg-info/SOURCES.txt
gpsimy.egg-info/dependency_links.txt
gpsimy.egg-info/not-zip-safe
gpsimy.egg-info/top_level.txt
gpsimy/models/__init__.py
gpsimy/models/device.py
gpsimy/models/event.py
gpsimy/models/message.py
gpsimy/models/position.py