Metadata-Version: 1.0
Name: gpsimy
Version: 0.1.3
Summary: GPS Position and tracker abstraction
Home-page: https://github.com/gamikun/gpsimy
Author: Gamaliel Espinoza Macedo
Author-email: gamaliel.espinoza@gmail.com
License: UNKNOWN
Platform: UNKNOWN
